sofastats_app/__init__.py
sofastats_app/docs_only.py
sofastats_app/ui/__init__.py
sofastats_app/ui/charts_and_tables.py
sofastats_app/ui/conf.py
sofastats_app/ui/data.csv
sofastats_app/ui/data.py
sofastats_app/ui/panel_server.py
sofastats_app/ui/state.py
sofastats_app/ui/ui.py
sofastats_app/ui/utils.py
sofastats_app/ui/images/anova_mean_things.svg
sofastats_app/ui/images/bunny_head_small.svg
sofastats_app/ui/images/crusty_walrus.svg
sofastats_app/ui/images/ttest_tea.svg
sofastats_app/ui/stats/__init__.py
sofastats_app/ui/stats/anova_form.py
sofastats_app/ui/stats/stats_chooser.py
sofastats_app/ui/stats/stats_config.py
sofastats_app/ui/stats/stats_tab.py
sofastats_app/ui/ui_template/__init__.py
sofastats_app/ui/ui_template/chocolate.css
sofastats_app/ui/ui_template/chocolate.html
sofastats-0.11.1.dist-info/METADATA
sofastats-0.11.1.dist-info/WHEEL
sofastats-0.11.1.dist-info/entry_points.txt
sofastats-0.11.1.dist-info/licenses/LICENSE
sofastats-0.11.1.dist-info/RECORD
