Metadata-Version: 2.4
Name: sofastats
Version: 0.11.1
Summary: SOFA Stats - no sweat stats!
Author-email: Grant Paton-Simpson <grant@sofastatistics.com>
License-File: LICENSE
Classifier: Development Status :: 1 - Planning
Requires-Python: >=3.11
Requires-Dist: panel>=1.7.5
Requires-Dist: sofastats-lib>=0.10.8
